[
  {
    "title": "Money Heist",
    "year": "2017",
    "category": "Crime, Drama, Thriller",
    "logo": "https://upload.wikimedia.org/wikipedia/en/4/45/Money_Heist.jpg",
    "episodes": [
      { "title": "Episode 1", "url": "https://example.com/moneyheist-ep1.mp4" },
      { "title": "Episode 2", "url": "https://example.com/moneyheist-ep2.mp4" },
      { "title": "Episode 3", "url": "https://example.com/moneyheist-ep3.mp4" }
    ]
  },
  {
    "title": "Stranger Things",
    "year": "2016",
    "category": "Drama, Fantasy, Horror",
    "logo": "https://upload.wikimedia.org/wikipedia/en/f/f7/Stranger_Things_logo.png",
    "episodes": [
      { "title": "Episode 1", "url": "https://example.com/strangerthings-ep1.mp4" },
      { "title": "Episode 2", "url": "https://example.com/strangerthings-ep2.mp4" }
    ]
  },
  {
    "title": "Breaking Bad",
    "year": "2008",
    "category": "Crime, Drama, Thriller",
    "logo": "https://upload.wikimedia.org/wikipedia/en/6/61/Breaking_Bad_title_card.png",
    "episodes": [
      { "title": "Episode 1", "url": "https://example.com/breakingbad-ep1.mp4" },
      { "title": "Episode 2", "url": "https://example.com/breakingbad-ep2.mp4" },
      { "title": "Episode 3", "url": "https://example.com/breakingbad-ep3.mp4" }
    ]
  }
]
